webauto/__init__.py
webauto-0.1.0.dist-info/METADATA
webauto-0.1.0.dist-info/WHEEL
webauto-0.1.0.dist-info/top_level.txt
webauto-0.1.0.dist-info/RECORD
