Metadata-Version: 2.4
Name: webauto
Version: 0.1.0
Summary: Add your description here
Requires-Python: >=3.13
Requires-Dist: cdpkits>=1.2.7
